pagos/__init__.py
pagos/builtin_models.py
pagos/constants.py
pagos/core.py
pagos/gas.py
pagos/modelling.py
pagos/plotting.py
pagos/units.py
pagos/water.py
pagos-0.5.4.dist-info/licenses/LICENSE
pagos-0.5.4.dist-info/METADATA
pagos-0.5.4.dist-info/WHEEL
pagos-0.5.4.dist-info/top_level.txt
pagos-0.5.4.dist-info/RECORD
