Metadata-Version: 2.4
Name: pagos
Version: 0.5.4
Summary: Python Analysis of Groundwater and Ocean Samples
Author-email: Stanley Scott <sscott@iup.uni-heidelberg.de>
Project-URL: Homepage, https://github.com/TeamPAGOS/PAGOS
Classifier: Programming Language :: Python :: 3
Classifier: License :: OSI Approved :: BSD License
Classifier: Operating System :: OS Independent
Requires-Python: >=3.12
License-File: LICENSE
Requires-Dist: lmfit>=1.2.2
Requires-Dist: matplotlib>=3.8.2
Requires-Dist: numpy>=1.26.2
Requires-Dist: pandas>=2.2.0
Requires-Dist: Pint>=0.24.4
Requires-Dist: tqdm>=4.66.2
Requires-Dist: uncertainties>=3.1.7
Requires-Dist: wrapt>=1.16.0
Provides-Extra: docs
Requires-Dist: mkdocs; extra == "docs"
Requires-Dist: mkdocs-material; extra == "docs"
Requires-Dist: mike; extra == "docs"
Dynamic: license-file
